pimidipy/__init__.py
pimidipy/pimidipy.py
pimidipy/type_wrappers.py
pimidipy-0.1.2.post4.dist-info/COPYING
pimidipy-0.1.2.post4.dist-info/METADATA
pimidipy-0.1.2.post4.dist-info/WHEEL
pimidipy-0.1.2.post4.dist-info/top_level.txt
pimidipy-0.1.2.post4.dist-info/RECORD
