Metadata-Version: 2.1
Name: pimidipy
Version: 0.1.2.post4
Summary: pimidipy MIDI processing library
Author-email: Blokas <hello@blokas.io>
Project-URL: Homepage, https://blokas.io/pimidi/
Project-URL: Community, https://community.blokas.io/c/pimidi/26
Project-URL: Documentation, https://blokas.io/pimidi/docs/pimidipy/
Project-URL: Repository, https://github.com/blokaslabs/pimidipy
Project-URL: Issues, https://github.com/blokaslabs/pimidipy/issues
Classifier: Programming Language :: Python :: 3
Classifier: License :: OSI Approved :: GNU General Public License v3 (GPLv3)
Classifier: Operating System :: POSIX :: Linux
Requires-Python: >=3.9
License-File: COPYING
Requires-Dist: alsa_midi
Requires-Dist: python-dotenv
